README.rst
setup.py
twisted/plugins/mllp_plugin.py
twisted_hl7.egg-info/PKG-INFO
twisted_hl7.egg-info/SOURCES.txt
twisted_hl7.egg-info/dependency_links.txt
twisted_hl7.egg-info/requires.txt
twisted_hl7.egg-info/top_level.txt
twistedhl7/__init__.py
twistedhl7/mllp.py
twistedhl7/receiver.py