Metadata-Version: 1.1
Name: twisted-hl7
Version: 0.2.2
Summary: Async Twisted server implementation of Health Level 7 MLLP
Home-page: http://twisted-hl7.readthedocs.org
Author: John Paulett
Author-email: john@paulett.org
License: BSD
Keywords: HL7,Health Level 7,healthcare,health care,medical record,twisted
Platform: POSIX
Platform: Windows
Classifier: License :: OSI Approved :: BSD License
Classifier: Operating System :: OS Independent
Classifier: Programming Language :: Python
Classifier: Development Status :: 3 - Alpha
Classifier: Framework :: Twisted
Classifier: Intended Audience :: Developers
Classifier: Intended Audience :: Healthcare Industry
Classifier: Topic :: Communications
Classifier: Topic :: Scientific/Engineering :: Medical Science Apps.
Classifier: Topic :: Software Development :: Libraries :: Python Modules
Classifier: Topic :: System :: Networking
